mixpanel_async/__init__.py
mixpanel_async/async_buffered_consumer.py
mixpanel_py_async-0.3.0.dist-info/LICENSE.md
mixpanel_py_async-0.3.0.dist-info/METADATA
mixpanel_py_async-0.3.0.dist-info/WHEEL
mixpanel_py_async-0.3.0.dist-info/top_level.txt
mixpanel_py_async-0.3.0.dist-info/RECORD
